DeepNexAI_mlutils/__init__.py
DeepNexAI_mlutils/model_tools.py
deepnexai_mlutils-1.1.0.dist-info/METADATA
deepnexai_mlutils-1.1.0.dist-info/WHEEL
deepnexai_mlutils-1.1.0.dist-info/top_level.txt
deepnexai_mlutils-1.1.0.dist-info/RECORD
