Metadata-Version: 2.1
Name: deepnexai_mlutils
Version: 1.1.0
Summary: TensorFlow model visualizer & dark summary generator
Author: DeepNexAI
Requires-Python: >=3.8
Requires-Dist: tensorflow
Requires-Dist: pillow
Requires-Dist: pydot
Requires-Dist: graphviz
